vnpy_ifind/__init__.py
vnpy_ifind/ifind_datafeed.py
vnpy_ifind-1.1.0.dist-info/METADATA
vnpy_ifind-1.1.0.dist-info/WHEEL
vnpy_ifind-1.1.0.dist-info/licenses/LICENSE
vnpy_ifind-1.1.0.dist-info/RECORD
